{
  "patch": {
    "version": "10.05",
    "take": "The changelog looks small. Then I played a night of comp and losing the opening duel stopped deciding the round.",
    "articleSlug": "patch-10-05-first-impressions"
  },
  "hotTakes": [
    "I keep losing my opening duel on 10.05 and winning the round anyway. Best patch this year.",
    "I rewatched the yetujey clip five times and I still don't think the peek decided that map.",
    "Vitality look like the only team in London that scrimmed real comps. Jamppi is playing like it."
  ],
  "clipOfTheWeek": "jamppi-1v4-ace-masters-london",
  "resources": [
    { "label": "VLR.gg", "url": "https://www.vlr.gg" },
    { "label": "Liquipedia", "url": "https://liquipedia.net/valorant" },
    { "label": "Patch notes", "url": "https://playvalorant.com/en-us/news/game-updates/" },
    { "label": "r/ValorantCompetitive", "url": "https://www.reddit.com/r/ValorantCompetitive/" }
  ]
}
